exif2findertags/__init__.py
exif2findertags/__main__.py
exif2findertags/_version.py
exif2findertags/cli.py
exif2findertags/datetime_formatter.py
exif2findertags/exiftofinder.py
exif2findertags/exiftool.py
exif2findertags/path_utils.py
exif2findertags/phototemplate.md
exif2findertags/phototemplate.py
exif2findertags/phototemplate.tx
exif2findertags/text_detection.py
exif2findertags-0.2.0.dist-info/LICENSE
exif2findertags-0.2.0.dist-info/METADATA
exif2findertags-0.2.0.dist-info/WHEEL
exif2findertags-0.2.0.dist-info/entry_points.txt
exif2findertags-0.2.0.dist-info/top_level.txt
exif2findertags-0.2.0.dist-info/RECORD
