Metadata-Version: 2.1
Name: exif2findertags
Version: 0.2.0
Summary: Read exif metadata from images with exiftool and write to MacOS Finder keywords
Home-page: https://github.com/RhetTbull/exif2findertags
Download-URL: https://github.com/RhetTbull/exif2findertags
Author: Rhet Turnbull
Author-email: rturnbull+git@gmail.com
License: License :: OSI Approved :: MIT License
Project-URL: GitHub, https://github.com/RhetTbull/exif2findertags
Classifier: Development Status :: 4 - Beta
Classifier: Environment :: MacOS X
Classifier: Intended Audience :: End Users/Desktop
Classifier: License :: OSI Approved :: MIT License
Classifier: Operating System :: MacOS :: MacOS X
Classifier: Programming Language :: Python :: 3.9
Classifier: Programming Language :: Python :: 3.10
Classifier: Programming Language :: Python :: 3.11
Classifier: Topic :: Software Development :: Libraries :: Python Modules
Requires-Python: >=3.9
License-File: LICENSE
Requires-Dist: wurlitzer (<4.0,>=3.0.3)
Requires-Dist: Click (<9.0,>=8.1.3)
Requires-Dist: cloup (<3.0,>=2.0.0)
Requires-Dist: osxmetadata (<2.0,>=1.2.2)
Requires-Dist: pathvalidate (<3.0,>=2.5.2)
Requires-Dist: pyobjc-core (<10.0,>=9.0)
Requires-Dist: pyobjc-framework-AVFoundation (<10.0,>=9.0)
Requires-Dist: pyobjc-framework-CoreServices (<10.0,>=9.0)
Requires-Dist: pyobjc-framework-Metal (<10.0,>=9.0)
Requires-Dist: pyobjc-framework-Quartz (<10.0,>=9.0)
Requires-Dist: pyobjc-framework-Vision (<10.0,>=9.0)
Requires-Dist: rich (<13.0,>=12.6.0)
Requires-Dist: textx (<4.0,>=3.0.0)
Requires-Dist: yaspin (<3.0,>=2.2.0)
